{"stat.useItem.minecraft.lapis_ore":6,"stat.walkOneCm":128504,"stat.useItem.minecraft.stone":567,"stat.leaveGame":13,"stat.useItem.minecraft.tnt":110,"stat.killEntity.Creeper":2,"stat.jump":1234,"stat.useItem.minecraft.sand":55,"stat.swimOneCm":1317,"stat.crouchOneCm":6379,"stat.sprintOneCm":79044,"stat.useItem.minecraft.diamond_block":12,"achievement.exploreAllBiomes":{"value":0,"progress":["Beach","DesertHills","River","Ocean","Plains","Desert"]},"stat.useItem.minecraft.cactus":28,"stat.killEntity.Skeleton":1,"achievement.openInventory":4,"stat.mobKills":4,"stat.flyOneCm":310410,"stat.playOneMinute":74465,"stat.useItem.minecraft.stone_sword":16,"stat.damageDealt":1050,"stat.killEntity.Zombie":1,"stat.timeSinceDeath":74465,"stat.useItem.minecraft.spawn_egg":1,"stat.diveOneCm":2273,"stat.useItem.minecraft.sandstone":213}