{"stat.walkOneCm":76405,"achievement.openInventory":6,"stat.useItem.minecraft.stone":143,"stat.useItem.minecraft.flint_and_steel":225,"stat.leaveGame":7,"stat.flyOneCm":130949,"stat.jump":654,"stat.useItem.minecraft.sand":67,"stat.playOneMinute":16610,"stat.damageDealt":10,"stat.crouchOneCm":8876,"stat.timeSinceDeath":16610,"stat.sprintOneCm":34337,"achievement.exploreAllBiomes":{"value":0,"progress":["Beach","DesertHills","River","Desert"]},"stat.useItem.minecraft.cactus":171,"stat.useItem.minecraft.sandstone":96}