{"stat.walkOneCm":64613,"achievement.openInventory":7,"stat.useItem.minecraft.stone":967,"stat.useItem.minecraft.flint_and_steel":1,"stat.leaveGame":8,"stat.useItem.minecraft.tnt":17,"stat.flyOneCm":237594,"stat.jump":903,"stat.useItem.minecraft.sand":96,"stat.swimOneCm":698,"stat.playOneMinute":21660,"stat.climbOneCm":743,"stat.damageDealt":65,"stat.crouchOneCm":2753,"stat.timeSinceDeath":21660,"stat.sprintOneCm":46932,"achievement.exploreAllBiomes":{"value":0,"progress":["Beach","DesertHills","River","Desert"]}}