{"stat.useItem.minecraft.glass":17,"stat.walkOneCm":111331,"achievement.openInventory":8,"stat.useItem.minecraft.stone":186,"stat.leaveGame":14,"stat.useItem.minecraft.tnt":298,"stat.flyOneCm":262196,"stat.jump":759,"stat.useItem.minecraft.sand":5,"stat.playOneMinute":66343,"stat.crouchOneCm":4199,"stat.useItem.minecraft.wool":9,"stat.timeSinceDeath":66343,"stat.useItem.minecraft.redstone_torch":8,"stat.sprintOneCm":70091,"achievement.exploreAllBiomes":{"value":0,"progress":["Beach","River","Ocean","Plains","Desert"]},"stat.useItem.minecraft.cactus":36}